LICENSE
MANIFEST.in
README.md
setup.cfg
setup.py
libpy_simdjson/__init__.py
libpy_simdjson/parser.cc
libpy_simdjson/simdjson.cpp
libpy_simdjson/simdjson.h
libpy_simdjson.egg-info/PKG-INFO
libpy_simdjson.egg-info/SOURCES.txt
libpy_simdjson.egg-info/dependency_links.txt
libpy_simdjson.egg-info/not-zip-safe
libpy_simdjson.egg-info/requires.txt
libpy_simdjson.egg-info/top_level.txt
submodules/range-v3/include/module.modulemap
submodules/range-v3/include/concepts/compare.hpp
submodules/range-v3/include/concepts/concepts.hpp
submodules/range-v3/include/concepts/swap.hpp
submodules/range-v3/include/concepts/type_traits.hpp
submodules/range-v3/include/meta/meta.hpp
submodules/range-v3/include/meta/meta_fwd.hpp
submodules/range-v3/include/range/v3/action.hpp
submodules/range-v3/include/range/v3/algorithm.hpp
submodules/range-v3/include/range/v3/all.hpp
submodules/range-v3/include/range/v3/at.hpp
submodules/range-v3/include/range/v3/back.hpp
submodules/range-v3/include/range/v3/begin_end.hpp
submodules/range-v3/include/range/v3/compare.hpp
submodules/range-v3/include/range/v3/core.hpp
submodules/range-v3/include/range/v3/data.hpp
submodules/range-v3/include/range/v3/distance.hpp
submodules/range-v3/include/range/v3/empty.hpp
submodules/range-v3/include/range/v3/front.hpp
submodules/range-v3/include/range/v3/functional.hpp
submodules/range-v3/include/range/v3/getlines.hpp
submodules/range-v3/include/range/v3/index.hpp
submodules/range-v3/include/range/v3/istream_range.hpp
submodules/range-v3/include/range/v3/iterator.hpp
submodules/range-v3/include/range/v3/iterator_range.hpp
submodules/range-v3/include/range/v3/numeric.hpp
submodules/range-v3/include/range/v3/range.hpp
submodules/range-v3/include/range/v3/range_access.hpp
submodules/range-v3/include/range/v3/range_concepts.hpp
submodules/range-v3/include/range/v3/range_for.hpp
submodules/range-v3/include/range/v3/range_fwd.hpp
submodules/range-v3/include/range/v3/range_traits.hpp
submodules/range-v3/include/range/v3/size.hpp
submodules/range-v3/include/range/v3/span.hpp
submodules/range-v3/include/range/v3/to_container.hpp
submodules/range-v3/include/range/v3/utility.hpp
submodules/range-v3/include/range/v3/version.hpp
