Metadata-Version: 2.1
Name: libpy-simdjson
Version: 0.2.0
Summary: Python bindings for smidjson, using libpy
Home-page: https://github.com/gerrymanoim/libpy_simdjson
Author: Gerry Manoim, Joe Jevnik
Author-email: Gerry Manoim <gerrymanoim@gmail.com>, Joe Jevnik <joejev@gmail.com>
License: Apache 2.0
Platform: UNKNOWN
Classifier: Development Status :: 4 - Beta
Classifier: License :: OSI Approved :: Apache Software License
Classifier: Natural Language :: English
Classifier: Topic :: Software Development
Classifier: Programming Language :: Python
Classifier: Programming Language :: Python :: 3.5
Classifier: Programming Language :: Python :: 3.6
Classifier: Programming Language :: Python :: 3.7
Classifier: Programming Language :: Python :: 3.8
Classifier: Programming Language :: Python :: Implementation :: CPython
Classifier: Programming Language :: C++
Classifier: Operating System :: POSIX
Classifier: Intended Audience :: Developers
Provides-Extra: test
Provides-Extra: benchmark
